easybmp/__init__.py
easybmp/main.py
easybmp-0.0.5.dist-info/LICENSE
easybmp-0.0.5.dist-info/METADATA
easybmp-0.0.5.dist-info/WHEEL
easybmp-0.0.5.dist-info/entry_points.txt
easybmp-0.0.5.dist-info/top_level.txt
easybmp-0.0.5.dist-info/RECORD
