Metadata-Version: 2.1
Name: easybmp
Version: 0.0.5
Summary: A Python library which can easily read / modify / compare / and other functions with .bmp files
License-File: LICENSE
